tikolu_uploader/__init__.py
tikolu_uploader/uploader.py
tikolu_uploader-1.0.0.dist-info/METADATA
tikolu_uploader-1.0.0.dist-info/WHEEL
tikolu_uploader-1.0.0.dist-info/top_level.txt
tikolu_uploader-1.0.0.dist-info/RECORD
