Metadata-Version: 2.4
Name: tikolu-uploader
Version: 1.0.0
Summary: A simple Python client for uploading images to tikolu.net/i
Author: AllahSolutions
License: MIT
Project-URL: Homepage, https://github.com/AllahSolutions/tikolu-uploader
Keywords: tikolu,image,uploader,api
Requires-Dist: requests>=2.0.0
